torchpack/__init__.py
torchpack/version.py
torchpack/callbacks/__init__.py
torchpack/callbacks/callback.py
torchpack/callbacks/checkpoint.py
torchpack/callbacks/inference.py
torchpack/callbacks/metainfo.py
torchpack/callbacks/metrics.py
torchpack/callbacks/progress.py
torchpack/callbacks/trackers.py
torchpack/callbacks/triggers.py
torchpack/callbacks/writers.py
torchpack/datasets/__init__.py
torchpack/datasets/dataset.py
torchpack/datasets/vision/__init__.py
torchpack/datasets/vision/cifar.py
torchpack/datasets/vision/imagenet.py
torchpack/distributed/__init__.py
torchpack/distributed/comm.py
torchpack/distributed/context.py
torchpack/environ/__init__.py
torchpack/environ/rundir.py
torchpack/launch/__init__.py
torchpack/launch/main.py
torchpack/launch/assets/__init__.py
torchpack/launch/assets/silentrun.py
torchpack/launch/launchers/__init__.py
torchpack/launch/launchers/drunner.py
torchpack/models/__init__.py
torchpack/models/utils.py
torchpack/models/vision/__init__.py
torchpack/models/vision/mobilenetv1.py
torchpack/models/vision/mobilenetv2.py
torchpack/models/vision/shufflenetv2.py
torchpack/nn/__init__.py
torchpack/nn/functional/__init__.py
torchpack/nn/functional/index.py
torchpack/train/__init__.py
torchpack/train/exception.py
torchpack/train/summary.py
torchpack/train/trainer.py
torchpack/utils/__init__.py
torchpack/utils/config.py
torchpack/utils/device.py
torchpack/utils/fs.py
torchpack/utils/git.py
torchpack/utils/humanize.py
torchpack/utils/imp.py
torchpack/utils/io.py
torchpack/utils/logging.py
torchpack/utils/matching.py
torchpack/utils/typing.py
torchpack-0.3.1.dist-info/METADATA
torchpack-0.3.1.dist-info/WHEEL
torchpack-0.3.1.dist-info/entry_points.txt
torchpack-0.3.1.dist-info/top_level.txt
torchpack-0.3.1.dist-info/RECORD
